tide_sim/__init__.py
tide_sim/models/__init__.py
tide_sim/models/joint.py
tide_sim/nodes/__init__.py
tide_sim/nodes/sim.py
tide_sim-0.2.0.dist-info/METADATA
tide_sim-0.2.0.dist-info/WHEEL
tide_sim-0.2.0.dist-info/licenses/LICENSE
tide_sim-0.2.0.dist-info/RECORD
