Metadata-Version: 2.4
Name: tide-sim
Version: 0.2.0
Summary: A package for adding a simulation environment to a tide robot
Project-URL: Homepage, https://github.com/yourusername/tide-sim
Project-URL: Documentation, https://github.com/yourusername/tide-sim#readme
Project-URL: Repository, https://github.com/yourusername/tide-sim.git
Project-URL: Issues, https://github.com/yourusername/tide-sim/issues
Author-email: Schreiber <schreiaj@gmail.com>
License: MIT
License-File: LICENSE
Keywords: pybullet,robotics,simulation,tide
Classifier: Development Status :: 3 - Alpha
Classifier: Intended Audience :: Developers
Classifier: Intended Audience :: Science/Research
Classifier: License :: OSI Approved :: MIT License
Classifier: Programming Language :: Python :: 3
Classifier: Programming Language :: Python :: 3.8
Classifier: Programming Language :: Python :: 3.9
Classifier: Programming Language :: Python :: 3.10
Classifier: Programming Language :: Python :: 3.11
Classifier: Topic :: Scientific/Engineering
Classifier: Topic :: Software Development :: Libraries :: Python Modules
Requires-Python: >=3.12
Requires-Dist: pybullet>=3.2.7
Requires-Dist: tide-sdk>=0.1.5
Provides-Extra: dev
Requires-Dist: black>=23.0; extra == 'dev'
Requires-Dist: isort>=5.0; extra == 'dev'
Requires-Dist: mypy>=1.0; extra == 'dev'
Requires-Dist: pytest-cov>=4.0; extra == 'dev'
Requires-Dist: pytest>=7.0; extra == 'dev'
Requires-Dist: ruff>=0.1.0; extra == 'dev'
